publish_poetry_test/__init__.py
publish_poetry_test/adapter.py
publish_poetry_test/rabbitmq_adapter.py
publish_poetry_test/test.py
publish_poetry_test-0.0.7.dist-info/LICENSE.txt
publish_poetry_test-0.0.7.dist-info/METADATA
publish_poetry_test-0.0.7.dist-info/WHEEL
publish_poetry_test-0.0.7.dist-info/top_level.txt
publish_poetry_test-0.0.7.dist-info/RECORD
